Metadata-Version: 2.1
Name: interactiontransformer
Version: 0.1.1
Summary: Extract interactions from complex model using SHAP and add to linear model..
Home-page: https://github.com/jlevy44/InteractionExtractor
Author: Joshua Levy
Author-email: joshualevy44@berkeley.edu
License: MIT
Platform: UNKNOWN
